AUTHORS
LICENSE.txt
MANIFEST.in
README.rst
requirements.txt
setup.py
doc/Makefile
doc/apidoc.rst
doc/conf.py
doc/configuration.png
doc/configuration.rst
doc/human.rst
doc/index.rst
doc/measurements.png
doc/measurements.rst
doc/overview.rst
doc/releasenotes.rst
doc/segment.rst
doc/solid.rst
doc/stadium.png
doc/usage.rst
misc/CFGtemplate.txt
misc/configuration.svg
misc/meastemplate.txt
misc/measurements.svg
misc/samplemeasurements/female1.txt
misc/samplemeasurements/male1.txt
misc/samplemeasurements/male2.txt
misc/samplemeasurements/male3.txt
misc/samplemeasurements/male4.txt
yeadon/__init__.py
yeadon/app.py
yeadon/exceptions.py
yeadon/gui.py
yeadon/human.py
yeadon/inertia.py
yeadon/segment.py
yeadon/solid.py
yeadon/ui.py
yeadon/utils.py
yeadon/version.py
yeadon.egg-info/PKG-INFO
yeadon.egg-info/SOURCES.txt
yeadon.egg-info/dependency_links.txt
yeadon.egg-info/entry_points.txt
yeadon.egg-info/requires.txt
yeadon.egg-info/top_level.txt
yeadon/tests/__init__.py
yeadon/tests/test_human.py
yeadon/tests/test_inertia.py
yeadon/tests/test_segment.py
yeadon/tests/test_solid.py
yeadon/tests/test_ui.py