Metadata-Version: 2.1
Name: yeadon
Version: 1.5.0
Summary: Estimates the inertial properties of a human.
Home-page: https://github.com/chrisdembia/yeadon/
Author: Chris Dembia
Author-email: chris530d@gmail.com
License: LICENSE.txt
Keywords: human inertia yeadon sports biomechanics gymnastics
Classifier: Development Status :: 5 - Production/Stable
Classifier: Intended Audience :: Science/Research
Classifier: Operating System :: OS Independent
Classifier: Programming Language :: Python :: 3.8
Classifier: Programming Language :: Python :: 3.9
Classifier: Programming Language :: Python :: 3.10
Classifier: Programming Language :: Python :: 3.11
Classifier: Programming Language :: Python :: 3.12
Classifier: Topic :: Scientific/Engineering :: Physics
License-File: LICENSE.txt
License-File: AUTHORS
Requires-Dist: numpy>=1.21.5
Requires-Dist: pyyaml>=5.4.1
Provides-Extra: gui
Requires-Dist: mayavi>=4.7.1; extra == "gui"
Provides-Extra: doc
Requires-Dist: sphinx>=4.3.2; extra == "doc"
Requires-Dist: numpydoc>=1.2; extra == "doc"
